[
    {
        "nomor": 1,
        "sub_modul": "Sesuai Halaman (TWK/TIU/TKP)",
        "pertanyaan": "Pertanyaan 1\nTidak dijawab\n1. ISTAL=______",
        "pilihan": [
            "Perapian",
            "Kandang Kuda",
            "Jamur",
            "Pasang",
            "Istana"
        ],
        "jawaban_benar": "Kandang Kuda",
        "pembahasan": "Istal = Kandang Kuda"
    },
    {
        "nomor": 2,
        "sub_modul": "Sesuai Halaman (TWK/TIU/TKP)",
        "pertanyaan": "Pertanyaan 2\nTidak dijawab\nKELAKAR=______",
        "pilihan": [
            "Tertawa",
            "Senang",
            "Goda",
            "Cacian",
            "Canda"
        ],
        "jawaban_benar": "Canda",
        "pembahasan": "Kelakar = (1) perkataan yang bersifat lucu untuk membuat orang tertawa (gembira); lawak; canda."
    },
    {
        "nomor": 3,
        "sub_modul": "Sesuai Halaman (TWK/TIU/TKP)",
        "pertanyaan": "Pertanyaan 3\nTidak dijawab\n3. GALAT=______",
        "pilihan": [
            "Pendek",
            "Rata-rata",
            "Ciri khas",
            "Batas hitungan",
            "Cacat"
        ],
        "jawaban_benar": "Cacat",
        "pembahasan": "Galat = kekeliruan, kesalahan; cacat."
    },
    {
        "nomor": 4,
        "sub_modul": "Sesuai Halaman (TWK/TIU/TKP)",
        "pertanyaan": "Pertanyaan 4\nTidak dijawab\nFIKSI > <______",
        "pilihan": [
            "Legenda",
            "Mitos",
            "Imajinasi",
            "Impian",
            "Nonfiksi"
        ],
        "jawaban_benar": "Nonfiksi",
        "pembahasan": "Lawan kata yang tepat untuk kata fiksi adalah kata non fiksi."
    },
    {
        "nomor": 5,
        "sub_modul": "Sesuai Halaman (TWK/TIU/TKP)",
        "pertanyaan": "Pertanyaan 5\nTidak dijawab\nSKEPTIS > <______",
        "pilihan": [
            "Semangat",
            "Tidakyakin",
            "Yakin",
            "Perjuangan",
            "Ragu-ragu"
        ],
        "jawaban_benar": "Ragu-ragu",
        "pembahasan": "5.\tSkeptis = Ragu-ragu. Lawan kata yang tepat untuk kata skeptis adalah kata yakin."
    },
    {
        "nomor": 6,
        "sub_modul": "Sesuai Halaman (TWK/TIU/TKP)",
        "pertanyaan": "Pertanyaan 6\nTidak dijawab\nMUSLIHAT > <______",
        "pilihan": [
            "Jujur",
            "Berani",
            "Sombong",
            "Parah",
            "Brutal"
        ],
        "jawaban_benar": "Jujur",
        "pembahasan": "6.\tMuslihat = Tipuan. Lawan kata yang tepat untuk kata muslihat adalah kata jujur."
    },
    {
        "nomor": 7,
        "sub_modul": "Sesuai Halaman (TWK/TIU/TKP)",
        "pertanyaan": "Pertanyaan 7\nTidak dijawab\nMAWAR : TANAMAN = ______ : ______",
        "pilihan": [
            "Pohon : Jati",
            "Anak : Ibu",
            "Kamar : Rumah",
            "Kucing : Tikus",
            "Singa : Binatang"
        ],
        "jawaban_benar": "Singa : Binatang",
        "pembahasan": "Mawar termasuk dalam jenis tanaman. Singa termasuk dalam jenis binatang."
    },
    {
        "nomor": 8,
        "sub_modul": "Sesuai Halaman (TWK/TIU/TKP)",
        "pertanyaan": "Pertanyaan 8\nTidak dijawab\nAIR : UAP = ______ : ______",
        "pilihan": [
            "Mendidih :Mencair",
            "Membeku :Menguap",
            "Es :Air",
            "Kabut :Asap",
            "Uap :Beku"
        ],
        "jawaban_benar": "Es :Air",
        "pembahasan": "Air jika dipanaskan akan menjadi uap. Es jika dipanaskan akan menjadi air."
    },
    {
        "nomor": 9,
        "sub_modul": "Sesuai Halaman (TWK/TIU/TKP)",
        "pertanyaan": "Pertanyaan 9\nTidak dijawab\nKAYU: ______ = BERAS : NASI GORENG",
        "pilihan": [
            "Pasak",
            "Kursitamu",
            "Gelondongan",
            "Papan",
            "Tripleks"
        ],
        "jawaban_benar": "Kursitamu",
        "pembahasan": "Beras jika dimasak bisa menjadi nasi goreng.\nKayu jika diolah bisa menjadi kursi tamu."
    },
    {
        "nomor": 10,
        "sub_modul": "Sesuai Halaman (TWK/TIU/TKP)",
        "pertanyaan": "Pertanyaan 10\nTidak dijawab\nMIKROSKOP : BAKTERIOLOG = SARUNG TANGAN :______",
        "pilihan": [
            "Apoteker",
            "Petinju",
            "Dokter",
            "Analis",
            "Peneliti"
        ],
        "jawaban_benar": "Petinju",
        "pembahasan": "Mikroskop adalah alat yang digunakan bakteriologi.\nSarung tangan adalah alat yang digunakan oleh petinju."
    },
    {
        "nomor": 11,
        "sub_modul": "Sesuai Halaman (TWK/TIU/TKP)",
        "pertanyaan": "Pertanyaan 11\nTidak dijawab\nKopi kualitas I dan kualitas II dicampur dengan perbandingan berat a : b. Harga kopi kualitas I dan kualitas II tiap kgmasing-masing adalah Rp 16.000,00 dan Rp 18.000,00. Jika harga kopi kualitas I naik 15%, sedangkan kopi kualitas II turun 10%, tetapi harga kopi campuran setiap kg tidak berubah, maka nilai a : b adalah…",
        "pilihan": [
            "3:4",
            "4:3",
            "8 : 9",
            "9 :8",
            "5 :6"
        ],
        "jawaban_benar": "9 :8",
        "pembahasan": "H1= (a(17600)+ 6(18000))/(a+b)\nHarga I naik 15% = 17.600\nHarga II turun 10% = 16.200\nH2= (a(17600)+6(16200))/(a+b)\nH1 = H2\na(16000)-6(18000)=a(17600)+b(16200)\n1600a=1800b\na/b=9/8"
    },
    {
        "nomor": 12,
        "sub_modul": "Sesuai Halaman (TWK/TIU/TKP)",
        "pertanyaan": "Pertanyaan 12\nTidak dijawab\nSeorang padagang menjual satu gulung kain teteron seharga Rp 75.000. Ia mendapatlaba 30% dari harga beli. Berapakah harga beli kain itu?",
        "pilihan": [
            "Rp53.500",
            "Rp52.500",
            "Rp 97.500",
            "Rp22.500",
            "Rp65.500"
        ],
        "jawaban_benar": "Rp52.500",
        "pembahasan": "12.\tMisalnya harga beli kain = a Harga jual kain = a + 30%\na + 30% = 75.000\na = 75.000 – (30% × 75.000)\n= 75.000 – 22.500\n= 52.500"
    },
    {
        "nomor": 13,
        "sub_modul": "Sesuai Halaman (TWK/TIU/TKP)",
        "pertanyaan": "Pertanyaan 13\nTidak dijawab\nBerat badan Ika adalah 37 kg. Setelah 4 bulan, berat badannya menjadi 39,082  kg. Berapa persenkah kenaikan berat badan Ika ?",
        "pilihan": [
            "5,783%",
            "5,627%",
            "5,310%",
            "4,302%",
            "4,289%"
        ],
        "jawaban_benar": "5,627%",
        "pembahasan": "% kenaikan = (39,082-37)/37×100%\n= 2,082/37=5,627%"
    },
    {
        "nomor": 14,
        "sub_modul": "Sesuai Halaman (TWK/TIU/TKP)",
        "pertanyaan": "Pertanyaan 14\nTidak dijawab\nP, Q, R, dan S adalah titik-titik yang secara beruntut berada pada satu garis. Jika panjang QR adalah 19% panjang RS, dan PR : PS = 2 : 5, maka persentase QR terhadap PR adalah …",
        "pilihan": [
            "A. 11,4%",
            "B. 28,5%",
            "C. 31,67%",
            "D. 47,5%",
            "E. 54,4%"
        ],
        "jawaban_benar": "B. 28,5%",
        "pembahasan": "PR : PS = 2 : 5 → PR : RS = 2 : 3\nQR : RS = 19 : 100 → QR : RS\n        = 19/33,33 : 3\nQR : PR = 19/33,33 : 2\n→ QR = 19/((33,33) × 2) PR\n→ QR = 19 : 66,67 PR → (dikali 3/2) \nMaka :\nQR = (28,5/100) PR = 28,5%."
    },
    {
        "nomor": 15,
        "sub_modul": "Sesuai Halaman (TWK/TIU/TKP)",
        "pertanyaan": "Pertanyaan 15\nTidak dijawab\nJika (a2 - b), (a > 0), dan (y= a2) manakah pernyataan berikut yang benar ?",
        "pilihan": [
            "A. x > y",
            "B. x < y",
            "C. x = y",
            "D. hubungan x dan y tidak dapat ditentukan",
            "E. x ≠y"
        ],
        "jawaban_benar": "B. x < y",
        "pembahasan": "Masukkan satu angka dengan syarat a > 0 (misal, 2).\na2 = b\tx2 = ((4a))/b\t\t  y = a2\n(2)2 = b\tx2 = 4.2/4                      y = 22\nb = 4\nx2 = 2\ny = 0\nberarti x < y"
    },
    {
        "nomor": 16,
        "sub_modul": "Sesuai Halaman (TWK/TIU/TKP)",
        "pertanyaan": "Pertanyaan 16\nTidak dijawab\nSoal ke 16",
        "pilihan": [
            "pilihan A",
            "pilihan B",
            "pilihan C",
            "pilihan D",
            "pilihan E"
        ],
        "jawaban_benar": "pilihan A",
        "pembahasan": ""
    },
    {
        "nomor": 17,
        "sub_modul": "Sesuai Halaman (TWK/TIU/TKP)",
        "pertanyaan": "Pertanyaan 17\nTidak dijawab\nTest soal dengan gambar",
        "pilihan": [
            "A"
        ],
        "jawaban_benar": "A",
        "pembahasan": ""
    },
    {
        "nomor": 18,
        "sub_modul": "Sesuai Halaman (TWK/TIU/TKP)",
        "pertanyaan": "Pertanyaan 18\nTidak dijawab\nNilai rata-rata ulangan matematika dari 30 siswa adalah 45. Jika nilai dari Jose digabungkan dengan kelompok itu, maka nilai rata-rata ulangan matematika menjadi 46. Berapakah nilai Jose ?",
        "pilihan": [
            "50.",
            "66.",
            "76.",
            "80.",
            "85."
        ],
        "jawaban_benar": "76.",
        "pembahasan": "Jumlah nilai dari 30 siswa\n= 30 × 45 = 1350\nJumlah nilai dari 31 siswa\n= 31 × 46 = 1426\nNilai Jose = 1426 – 1350 = 76.\n\nt = 16.11 – 11.53 = 4 jam 18 menit"
    },
    {
        "nomor": 19,
        "sub_modul": "Sesuai Halaman (TWK/TIU/TKP)",
        "pertanyaan": "Pertanyaan 19\nTidak dijawab\nSebuah truk berangkat dari kota A pada pukul 11.53 dan tiba di kota B yang berjarak240kmdarikotaApadapukul16.11 hari yang sama. Berapakah kecepatan rata-rata truk tersebut dalam menempuh perjalanan dari A ke B ?",
        "pilihan": [
            "1.494/240 km/jam.",
            "50 km/jam.",
            "16/1.200 km/jam.",
            "240/288 km/jam.",
            "65 km/jam."
        ],
        "jawaban_benar": "50 km/jam.",
        "pembahasan": "t = 16.11 – 11.53 = 4 jam 18 menit\n= 4 18/60=4,3 jam \nv=s/t=240/4,3=55,8km/jam→50km/jam"
    },
    {
        "nomor": 20,
        "sub_modul": "Sesuai Halaman (TWK/TIU/TKP)",
        "pertanyaan": "Pertanyaan 20\nTidak dijawab\nMega berangkat dari kota J pukul 06.00 dansampaidikotaYpukul12.30.Iaistirahat di kota X selama 30 menit untuk makan. Jika Mega mengendarai mobil dengan kecepatan 50 km/jam, berapakah jarak total kota J – Y ?",
        "pilihan": [
            "180 km.",
            "210 km.",
            "270 km.",
            "300 km.",
            "310 km."
        ],
        "jawaban_benar": "300 km.",
        "pembahasan": "Waktu tempuh Mega (t) = pukul 12.30 – pukul 06.00 – 30 menit  = 6 jam\nKecepatan Mega (v) = 50 km/jam\nJarak J – Y = 6 × 50 km = 300 km."
    },
    {
        "nomor": 21,
        "sub_modul": "Sesuai Halaman (TWK/TIU/TKP)",
        "pertanyaan": "Pertanyaan 21\nTidak dijawab\nDalam sebuah kandang ayam terdapat 65 ekor ayam. Diantaranya terdapat 16 ekor ayam jantan yang 9 ekor diantaranya berwarna hitam. Seluruh ayam yang berwarna hitam di dalam kandang itu berjumlah 44 ekor. Berapakah jumlah ayam betina yang tidak berwarna hitam ?",
        "pilihan": [
            "24 ekor.",
            "17 ekor.",
            "16 ekor.",
            "14 ekor.",
            "13 ekor."
        ],
        "jawaban_benar": "14 ekor.",
        "pembahasan": "Jenis ayam\tHitam\tTidak hitam\tJumlah\nAyam jantan \t   9\t                 7\t            16\nAyam betina\t  35                \t ?\t            49\nTotal\t          44\t                21\t            65\nJadi, ayam betina yang berwarna hitam\n= 49 – 35 = 14 ekor."
    },
    {
        "nomor": 22,
        "sub_modul": "Sesuai Halaman (TWK/TIU/TKP)",
        "pertanyaan": "Pertanyaan 22\nTidak dijawab\nSeekor kambing dapat menghabiskan rumput di suatu lapangan dalam waktu 4 minggu. Jika seekor sapi mampu menghabiskan rumput di lapangan yang sama dalam 3 minggu, berapa lama rumput akan habis jika kambing dan sapi makan bersama-sama di lapangan tersebut?",
        "pilihan": [
            "12 hari.",
            "18 hari.",
            "20 hari.",
            "24 hari.",
            "26 hari."
        ],
        "jawaban_benar": "12 hari.",
        "pembahasan": "1/waktu = 1/4 + 1/3 = 7/12\nWaktu = 12\nSapi dan kambing secara bersamaan dapat menghabiskan rumput satu lapangan selama 12 hari."
    },
    {
        "nomor": 23,
        "sub_modul": "Sesuai Halaman (TWK/TIU/TKP)",
        "pertanyaan": "Pertanyaan 23\nTidak dijawab\n11  12  13  10  13  14  15  12  15  16  …  …",
        "pilihan": [
            "13, 16.",
            "13, 17.",
            "14, 17.",
            "17, 14.",
            "19, 20."
        ],
        "jawaban_benar": "17, 14.",
        "pembahasan": "Tipe: 1 larik\nPola:\n11 12 13 10 13 14 15 12 15 16  17  14\n+1   +1    -3   +3   +1   +1    -3   +3   +1    +1   -3"
    },
    {
        "nomor": 24,
        "sub_modul": "Sesuai Halaman (TWK/TIU/TKP)",
        "pertanyaan": "Pertanyaan 24\nTidak dijawab\n1  1  2  4  7  13  25  …",
        "pilihan": [
            "31.",
            "38.",
            "49.",
            "50.",
            "55."
        ],
        "jawaban_benar": "49.",
        "pembahasan": "Tipe: tingkat\nPola: \n1   1   2   4    7   13    25    49"
    },
    {
        "nomor": 25,
        "sub_modul": "Sesuai Halaman (TWK/TIU/TKP)",
        "pertanyaan": "Pertanyaan 25\nTidak dijawab\n3  17  35  65  99  145 …",
        "pilihan": [
            "168.",
            "170.",
            "195.",
            "196.",
            "197."
        ],
        "jawaban_benar": "195.",
        "pembahasan": "Tipe: 2 larik dan tingkat\nPola:      +32\n\n\n   3    17    35   65    99   145   195\n   \n              +48               +48"
    },
    {
        "nomor": 26,
        "sub_modul": "Sesuai Halaman (TWK/TIU/TKP)",
        "pertanyaan": "Pertanyaan 26\nTidak dijawab\nSemua pekerja harus mengenakan topi pengaman. Sementara pekerja mengenakan sarungtangan.",
        "pilihan": [
            "Sementara pekerja tidak menggunakan topi pengaman.",
            "Semua pekerja tidak mengenakan topi pengaman dan sarung tangan.",
            "Sementara pekerja mengenakan topi pengaman dan sarung tangan.",
            "Sementara pekerja tidak mengenakan topi pengaman dan mengenakan sarung tangan.",
            "Sementara pekerja tidak mengenakan topi pengaman dan tidak mengenakan sarung tangan."
        ],
        "jawaban_benar": "Sementara pekerja mengenakan topi pengaman dan sarung tangan.",
        "pembahasan": "Sementara pekerja menggunakan topi pengaman dan sarung tangan."
    },
    {
        "nomor": 27,
        "sub_modul": "Sesuai Halaman (TWK/TIU/TKP)",
        "pertanyaan": "Pertanyaan 27\nTidak dijawab\nSemua anggota asosiasi profesi harus hadir dalam rapat. Sementara dokter adalah anggota asosiasi.",
        "pilihan": [
            "Semua yang hadir dalam rapat adalah dokter.",
            "Semua anggota rapat bukan anggota asosiasi profesi.",
            "Sementara peserta rapat adalah dokter.",
            "Semua dokter hadir dalam rapat.",
            "Semua yang hadir bukan dokter."
        ],
        "jawaban_benar": "Sementara peserta rapat adalah dokter.",
        "pembahasan": "Sementara peserta rapat adalah dokter."
    },
    {
        "nomor": 28,
        "sub_modul": "Sesuai Halaman (TWK/TIU/TKP)",
        "pertanyaan": "Pertanyaan 28\nTidak dijawab\nSemua seniman kreatif. Sementara ilmuan tidak kreatif.",
        "pilihan": [
            "Sementara ilmiah bukan seniman.",
            "Tidak ada seniman yang ilmuan.",
            "Sementara individu yang kreatif bukan seniman",
            "Sementara ilmuan kreatif.",
            "Sementara seniman kreatif."
        ],
        "jawaban_benar": "Sementara ilmuan kreatif.",
        "pembahasan": "28.\tSementara ilmuan kreatif."
    },
    {
        "nomor": 29,
        "sub_modul": "Sesuai Halaman (TWK/TIU/TKP)",
        "pertanyaan": "Pertanyaan 29\nTidak dijawab\nOrang mengantuk disorongkan bantal. Makna peribahasa di atas adalah …",
        "pilihan": [
            "Mendapatkan bantuan tak disangka-sangka.",
            "Mendapatkan keutungan besar.",
            "Mendapatkan musibah yang besar.",
            "Mendapatkan sesuatu yang sudah direncanakan.",
            "Mendapatkan sesuatu yang sangat idam-idamkan.."
        ],
        "jawaban_benar": "Mendapatkan sesuatu yang sangat idam-idamkan..",
        "pembahasan": "Peribahasa di atas dikiaskan kepada seseorang yang diberi sesuatu yang memang sangat diidam-idamkan atau sesuatu yang sesuai dengan keinginannya. Misalnya, orang yang ditimpa kesusahan mendapat pertolongan yang tidak diminta, orang yang sakit diberi obat yang dapat menyembuhkan sakitnya itu, ibarat orang mengantuk yang diberi bantal.\n“mendapatkan sesuatu yang memang sangat diidam-idamkan”."
    },
    {
        "nomor": 30,
        "sub_modul": "Sesuai Halaman (TWK/TIU/TKP)",
        "pertanyaan": "Pertanyaan 30\nTidak dijawab\nTertumbuk biduk dikelokkan, tertumbuk kata dipikiri.\nMakna peribahasa di atas adalah …",
        "pilihan": [
            "Menemukan masalah dalam pekerjaan.",
            "Bila mengerjakan sesuatu pekerjaan, harus beraturan.",
            "Mengerjakan suatu pekerjaan yang tidak dipikirkan.",
            "Mengerjakan sesuatu pekerjaan yang diperintahkan orang lain.",
            "Masalah datang setelah pekerjaan dilakukan.."
        ],
        "jawaban_benar": "Bila mengerjakan sesuatu pekerjaan, harus beraturan.",
        "pembahasan": "Biduk dan kata yang tertumbuk diumpakan dengan pekerjaan yang terhenti karena menemui kesulitan. Agar pekerjaan dapat diteruskan, hendaklah kita mencari daya upaya bagaimana keluar dari kesulitan itu. Jangan menyerah.\n\n“Bila mengerjakan sesuatu pekerjaan, harus beraturan”."
    }
]